.gitignore
.readthedocs.yml
CHANGELOG.rst
LICENSE.txt
MANIFEST.in
README.rst
setup.cfg
setup.py
docs/Makefile
docs/comparators.rst
docs/compilers.rst
docs/conf.py
docs/index.rst
docs/make.bat
docs/quickstart.rst
docs/syntaxsugar.rst
docs/toc.rst
rulez/__init__.py
rulez/action.py
rulez/dsl.py
rulez/engine.py
rulez/operator.py
rulez/transformer.py
rulez.egg-info/PKG-INFO
rulez.egg-info/SOURCES.txt
rulez.egg-info/dependency_links.txt
rulez.egg-info/entry_points.txt
rulez.egg-info/not-zip-safe
rulez.egg-info/requires.txt
rulez.egg-info/top_level.txt
rulez/compiler/__init__.py
rulez/compiler/elasticsearch/__init__.py
rulez/compiler/elasticsearch/operator.py
rulez/compiler/native/__init__.py
rulez/compiler/native/action.py
rulez/compiler/native/operator.py
rulez/compiler/sqlalchemy/__init__.py
rulez/compiler/sqlalchemy/action.py
rulez/compiler/sqlalchemy/operator.py
tests/common.py
tests/test_dsl.py
tests/test_elasticsearch_condition.py
tests/test_native_businessrule.py
tests/test_native_condition.py
tests/test_sqlalchemy_businessrule.py
tests/test_sqlalchemy_condition.py
tests/test_transform.py