Metadata-Version: 2.1
Name: rulez
Version: 0.1.4
Summary: Simple business rules engine configurable using YAML/JSON
Home-page: http://github.com/abyres/
Author: Izhar Firdaus
Author-email: izhar@abyres.net
License: MIT
Keywords: business-rules rules reg
Platform: UNKNOWN
Provides-Extra: test
